{
	"spritesrc":"assets/animations/warningbeacon.png",
	"animations":[{
			"name":"allclear",
			"frames":[{
					"duration":200,
					"x":0,
					"y":104,
					"w":20,
					"h":104
				},
				{
					"duration":200,
					"x":20,
					"y":104,
					"w":20,
					"h":104
				},
				{
					"duration":200,
					"x":40,
					"y":104,
					"w":20,
					"h":104
				}
			]
		},
		{
			"name":"warning",
			"frames":[{
					"duration":200,
					"x":0,
					"y":0,
					"w":20,
					"h":104
				},
				{
					"duration":200,
					"x":20,
					"y":0,
					"w":20,
					"h":104
				},
				{
					"duration":200,
					"x":40,
					"y":0,
					"w":20,
					"h":104
				}
			]
		}
	]
}